drf_anonymous_login/__init__.py
drf_anonymous_login/admin.py
drf_anonymous_login/authentication.py
drf_anonymous_login/models.py
drf_anonymous_login/views.py
drf_anonymous_login/management/__init__.py
drf_anonymous_login/management/commands/__init__.py
drf_anonymous_login/management/commands/cleanup_tokens.py
drf_anonymous_login/migrations/0001_initial.py
drf_anonymous_login/migrations/0002_anonymous_login_expiration_datetime.py
drf_anonymous_login/migrations/__init__.py
drf_anonymous_login-1.2.1.dist-info/licenses/LICENSE
drf_anonymous_login-1.2.1.dist-info/METADATA
drf_anonymous_login-1.2.1.dist-info/WHEEL
drf_anonymous_login-1.2.1.dist-info/top_level.txt
drf_anonymous_login-1.2.1.dist-info/RECORD
