Metadata-Version: 2.4
Name: drf-anonymous-login
Version: 1.2.1
Summary: Django rest framework module to allow login via token (without User instance).
License: MIT
Project-URL: Homepage, https://github.com/anexia/drf-anonymous-login
Project-URL: Repository, https://github.com/anexia/drf-anonymous-login
Classifier: Development Status :: 3 - Alpha
Classifier: Intended Audience :: Developers
Classifier: Programming Language :: Python :: 3
Classifier: Programming Language :: Python :: 3.10
Classifier: Programming Language :: Python :: 3.11
Classifier: Programming Language :: Python :: 3.12
Classifier: Programming Language :: Python :: 3.13
Classifier: Programming Language :: Python :: 3.14
Requires-Python: >=3.10
License-File: LICENSE
Requires-Dist: django<5.2,>=4.2
Requires-Dist: djangorestframework<3.16,>=3.15
Provides-Extra: dev
Requires-Dist: coverage<7.7,>=7.6.2; extra == "dev"
Requires-Dist: twine<5.2,>=5.1.1; extra == "dev"
Requires-Dist: pre-commit<4.1,>=4.0.1; extra == "dev"
Requires-Dist: setuptools-scm>=8.0; extra == "dev"
Dynamic: license-file
